sravanthi/__init__.py
i_am_sravanthi-0.1.dist-info/METADATA
i_am_sravanthi-0.1.dist-info/WHEEL
i_am_sravanthi-0.1.dist-info/top_level.txt
i_am_sravanthi-0.1.dist-info/RECORD
